[{"zip":"02641","city":"East Dennis","state":"MA","lat":41.7426,"long":-70.162},{"zip":"02642","city":"Eastham","state":"MA","lat":41.8408,"long":-69.9849},{"zip":"02643","city":"East Orleans","state":"MA","lat":41.7843,"long":-69.962},{"zip":"02644","city":"Forestdale","state":"MA","lat":41.6827,"long":-70.5143},{"zip":"02645","city":"Harwich","state":"MA","lat":41.7008,"long":-70.0579},{"zip":"02646","city":"Harwich Port","state":"MA","lat":41.6703,"long":-70.0722},{"zip":"02647","city":"Hyannis Port","state":"MA","lat":41.635,"long":-70.3063},{"zip":"02648","city":"Marstons Mills","state":"MA","lat":41.6703,"long":-70.4163},{"zip":"02649","city":"Mashpee","state":"MA","lat":41.6181,"long":-70.4854}]
