[{"zip":"52801","city":"Davenport","state":"IA","lat":41.5208,"long":-90.5745},{"zip":"52802","city":"Davenport","state":"IA","lat":41.5164,"long":-90.6141},{"zip":"52803","city":"Davenport","state":"IA","lat":41.5385,"long":-90.5613},{"zip":"52804","city":"Davenport","state":"IA","lat":41.5386,"long":-90.6115},{"zip":"52805","city":"Davenport","state":"IA","lat":41.613,"long":-90.6063},{"zip":"52806","city":"Davenport","state":"IA","lat":41.5733,"long":-90.6038},{"zip":"52807","city":"Davenport","state":"IA","lat":41.5618,"long":-90.5403},{"zip":"52808","city":"Davenport","state":"IA","lat":41.613,"long":-90.6063},{"zip":"52809","city":"Davenport","state":"IA","lat":41.613,"long":-90.6063}]
