[{"zip":"54762","city":"Prairie Farm","state":"WI","lat":45.2462,"long":-91.9742},{"zip":"54768","city":"Stanley","state":"WI","lat":44.9689,"long":-90.9389},{"zip":"54763","city":"Ridgeland","state":"WI","lat":45.1868,"long":-91.879},{"zip":"54764","city":"Rock Falls","state":"WI","lat":44.7186,"long":-91.6899},{"zip":"54765","city":"Sand Creek","state":"WI","lat":45.1429,"long":-91.6998},{"zip":"54769","city":"Stockholm","state":"WI","lat":44.5084,"long":-92.2326},{"zip":"54761","city":"Plum City","state":"WI","lat":44.636,"long":-92.1837},{"zip":"54767","city":"Spring Valley","state":"WI","lat":44.8356,"long":-92.2906},{"zip":"54766","city":"Sheldon","state":"WI","lat":45.3182,"long":-90.9141},{"zip":"54760","city":"Pigeon Falls","state":"WI","lat":44.4249,"long":-91.2074}]
