[{"zip":"56663","city":"Pennington","state":"MN","lat":47.4651,"long":-94.4834},{"zip":"56666","city":"Ponemah","state":"MN","lat":48.0372,"long":-94.917},{"zip":"56667","city":"Puposky","state":"MN","lat":47.7436,"long":-94.9803},{"zip":"56662","city":"Outing","state":"MN","lat":46.8375,"long":-93.9443},{"zip":"56660","city":"Mizpah","state":"MN","lat":47.9495,"long":-94.1467},{"zip":"56661","city":"Northome","state":"MN","lat":47.844,"long":-94.2043},{"zip":"56668","city":"Ranier","state":"MN","lat":48.613,"long":-93.3488},{"zip":"56669","city":"Kabetogama","state":"MN","lat":48.2463,"long":-93.7842}]
