[{"zip":"56683","city":"Tenstrike","state":"MN","lat":47.6566,"long":-94.6747},{"zip":"56685","city":"Waskish","state":"MN","lat":48.177,"long":-94.5037},{"zip":"56687","city":"Wilton","state":"MN","lat":47.5036,"long":-95.0011},{"zip":"56680","city":"Spring Lake","state":"MN","lat":47.6359,"long":-93.922},{"zip":"56681","city":"Squaw Lake","state":"MN","lat":47.6362,"long":-94.1475},{"zip":"56688","city":"Wirt","state":"MN","lat":47.7462,"long":-93.963},{"zip":"56686","city":"Williams","state":"MN","lat":48.8022,"long":-94.9556},{"zip":"56684","city":"Trail","state":"MN","lat":47.7478,"long":-95.7607},{"zip":"56682","city":"Swift","state":"MN","lat":48.8533,"long":-95.2213}]
