[{"zip":"62262","city":"Mulberry Grove","state":"IL","lat":38.9311,"long":-89.2463},{"zip":"62265","city":"New Baden","state":"IL","lat":38.5315,"long":-89.6922},{"zip":"62266","city":"New Memphis","state":"IL","lat":38.4857,"long":-89.6816},{"zip":"62261","city":"Modoc","state":"IL","lat":38.0507,"long":-90.0163},{"zip":"62260","city":"Millstadt","state":"IL","lat":38.4443,"long":-90.0888},{"zip":"62264","city":"New Athens","state":"IL","lat":38.316,"long":-89.8728},{"zip":"62269","city":"O Fallon","state":"IL","lat":38.5718,"long":-89.8957},{"zip":"62263","city":"Nashville","state":"IL","lat":38.3352,"long":-89.3841},{"zip":"62268","city":"Oakdale","state":"IL","lat":38.2573,"long":-89.596}]
