[{"zip":"74131","city":"Tulsa","state":"OK","lat":36.0557,"long":-96.0602},{"zip":"74127","city":"Tulsa","state":"OK","lat":36.1576,"long":-96.0311},{"zip":"74101","city":"Tulsa","state":"OK","lat":36.0391,"long":-95.8687},{"zip":"74102","city":"Tulsa","state":"OK","lat":36.154,"long":-95.9928},{"zip":"74103","city":"Tulsa","state":"OK","lat":36.1539,"long":-95.9954},{"zip":"74104","city":"Tulsa","state":"OK","lat":36.1464,"long":-95.9526},{"zip":"74105","city":"Tulsa","state":"OK","lat":36.0948,"long":-95.9655},{"zip":"74106","city":"Tulsa","state":"OK","lat":36.1883,"long":-95.986},{"zip":"74107","city":"Tulsa","state":"OK","lat":36.1042,"long":-96.0244},{"zip":"74108","city":"Tulsa","state":"OK","lat":36.1499,"long":-95.7923},{"zip":"74110","city":"Tulsa","state":"OK","lat":36.1803,"long":-95.9525},{"zip":"74112","city":"Tulsa","state":"OK","lat":36.147,"long":-95.907},{"zip":"74114","city":"Tulsa","state":"OK","lat":36.1262,"long":-95.9408},{"zip":"74115","city":"Tulsa","state":"OK","lat":36.1754,"long":-95.9112},{"zip":"74116","city":"Tulsa","state":"OK","lat":36.175,"long":-95.8477},{"zip":"74117","city":"Tulsa","state":"OK","lat":36.2393,"long":-95.8979},{"zip":"74119","city":"Tulsa","state":"OK","lat":36.1407,"long":-95.9902},{"zip":"74120","city":"Tulsa","state":"OK","lat":36.1442,"long":-95.9734},{"zip":"74121","city":"Tulsa","state":"OK","lat":36.1398,"long":-96.0297},{"zip":"74126","city":"Tulsa","state":"OK","lat":36.2383,"long":-95.9931},{"zip":"74128","city":"Tulsa","state":"OK","lat":36.1459,"long":-95.8514},{"zip":"74129","city":"Tulsa","state":"OK","lat":36.1259,"long":-95.8654},{"zip":"74130","city":"Tulsa","state":"OK","lat":36.2395,"long":-95.9596},{"zip":"74132","city":"Tulsa","state":"OK","lat":36.064,"long":-96.0251},{"zip":"74133","city":"Tulsa","state":"OK","lat":36.0467,"long":-95.8841},{"zip":"74134","city":"Tulsa","state":"OK","lat":36.1162,"long":-95.8225},{"zip":"74135","city":"Tulsa","state":"OK","lat":36.0976,"long":-95.9228},{"zip":"74136","city":"Tulsa","state":"OK","lat":36.0605,"long":-95.9452},{"zip":"74137","city":"Tulsa","state":"OK","lat":36.0284,"long":-95.9306},{"zip":"74141","city":"Tulsa","state":"OK","lat":36.1398,"long":-96.0297},{"zip":"74145","city":"Tulsa","state":"OK","lat":36.0934,"long":-95.8856},{"zip":"74146","city":"Tulsa","state":"OK","lat":36.1093,"long":-95.8506},{"zip":"74147","city":"Tulsa","state":"OK","lat":36.1398,"long":-96.0297},{"zip":"74148","city":"Tulsa","state":"OK","lat":36.1398,"long":-96.0297},{"zip":"74149","city":"Tulsa","state":"OK","lat":36.1398,"long":-96.0297},{"zip":"74150","city":"Tulsa","state":"OK","lat":36.1398,"long":-96.0297},{"zip":"74152","city":"Tulsa","state":"OK","lat":36.1398,"long":-96.0297},{"zip":"74153","city":"Tulsa","state":"OK","lat":36.1398,"long":-96.0297},{"zip":"74155","city":"Tulsa","state":"OK","lat":36.1398,"long":-96.0297},{"zip":"74156","city":"Tulsa","state":"OK","lat":36.3024,"long":-95.9605},{"zip":"74157","city":"Tulsa","state":"OK","lat":36.1398,"long":-96.0297},{"zip":"74158","city":"Tulsa","state":"OK","lat":36.1398,"long":-96.0297},{"zip":"74159","city":"Tulsa","state":"OK","lat":36.0772,"long":-96.0835},{"zip":"74169","city":"Tulsa","state":"OK","lat":36.1398,"long":-96.0297},{"zip":"74170","city":"Tulsa","state":"OK","lat":36.1398,"long":-96.0297},{"zip":"74171","city":"Tulsa","state":"OK","lat":36.154,"long":-95.9928},{"zip":"74172","city":"Tulsa","state":"OK","lat":36.1543,"long":-95.9923},{"zip":"74182","city":"Tulsa","state":"OK","lat":36.154,"long":-95.9928},{"zip":"74186","city":"Tulsa","state":"OK","lat":36.154,"long":-95.9928},{"zip":"74187","city":"Tulsa","state":"OK","lat":36.154,"long":-95.9928},{"zip":"74192","city":"Tulsa","state":"OK","lat":36.154,"long":-95.9928},{"zip":"74193","city":"Tulsa","state":"OK","lat":36.1398,"long":-96.0297}]
