[{"zip":"77442","city":"Garwood","state":"TX","lat":29.476,"long":-96.4919},{"zip":"77441","city":"Fulshear","state":"TX","lat":29.7217,"long":-95.8977},{"zip":"77444","city":"Guy","state":"TX","lat":29.3327,"long":-95.7702},{"zip":"77447","city":"Hockley","state":"TX","lat":30.0729,"long":-95.8104},{"zip":"77449","city":"Katy","state":"TX","lat":29.8323,"long":-95.736},{"zip":"77440","city":"Elmaton","state":"TX","lat":28.876,"long":-96.1434},{"zip":"77445","city":"Hempstead","state":"TX","lat":30.092,"long":-96.0716},{"zip":"77446","city":"Prairie View","state":"TX","lat":30.0836,"long":-95.9866},{"zip":"77443","city":"Glen Flora","state":"TX","lat":29.3475,"long":-96.1933},{"zip":"77448","city":"Hungerford","state":"TX","lat":29.4137,"long":-96.0929}]
