[{"zip":"86401","city":"Kingman","state":"AZ","lat":35.1328,"long":-113.7033},{"zip":"86402","city":"Kingman","state":"AZ","lat":35.2632,"long":-114.0637},{"zip":"86403","city":"Lake Havasu City","state":"AZ","lat":34.4814,"long":-114.3483},{"zip":"86404","city":"Lake Havasu City","state":"AZ","lat":34.5575,"long":-114.3307},{"zip":"86405","city":"Lake Havasu City","state":"AZ","lat":34.4839,"long":-114.3225},{"zip":"86406","city":"Lake Havasu City","state":"AZ","lat":34.4228,"long":-114.125},{"zip":"86409","city":"Kingman","state":"AZ","lat":35.2633,"long":-114.0223}]
