[{"zip":"91770","city":"Rosemead","state":"CA","lat":34.0658,"long":-118.0853},{"zip":"91771","city":"Rosemead","state":"CA","lat":34.0806,"long":-118.0728},{"zip":"91772","city":"Rosemead","state":"CA","lat":34.0806,"long":-118.0728},{"zip":"91773","city":"San Dimas","state":"CA","lat":34.1023,"long":-117.8169},{"zip":"91775","city":"San Gabriel","state":"CA","lat":34.1155,"long":-118.0857},{"zip":"91776","city":"San Gabriel","state":"CA","lat":34.089,"long":-118.0955},{"zip":"91778","city":"San Gabriel","state":"CA","lat":34.0961,"long":-118.1058}]
