[{"zip":"92602","city":"Irvine","state":"CA","lat":33.7419,"long":-117.7467},{"zip":"92603","city":"Irvine","state":"CA","lat":33.6245,"long":-117.794},{"zip":"92604","city":"Irvine","state":"CA","lat":33.6899,"long":-117.7868},{"zip":"92605","city":"Huntington Beach","state":"CA","lat":33.7151,"long":-118.0077},{"zip":"92606","city":"Irvine","state":"CA","lat":33.6951,"long":-117.8224},{"zip":"92607","city":"Laguna Niguel","state":"CA","lat":33.5269,"long":-117.7117},{"zip":"92609","city":"El Toro","state":"CA","lat":33.624,"long":-117.6908}]
