[{"zip":"98121","city":"Seattle","state":"WA","lat":47.6151,"long":-122.3447},{"zip":"98122","city":"Seattle","state":"WA","lat":47.6116,"long":-122.3056},{"zip":"98124","city":"Seattle","state":"WA","lat":47.6062,"long":-122.3321},{"zip":"98125","city":"Seattle","state":"WA","lat":47.717,"long":-122.3015},{"zip":"98126","city":"Seattle","state":"WA","lat":47.5444,"long":-122.3735},{"zip":"98127","city":"Seattle","state":"WA","lat":47.6063,"long":-122.3308},{"zip":"98129","city":"Seattle","state":"WA","lat":47.6062,"long":-122.3321}]
